MANIFEST.in
README.md
setup.py
latimes_statestyle.egg-info/PKG-INFO
latimes_statestyle.egg-info/SOURCES.txt
latimes_statestyle.egg-info/dependency_links.txt
latimes_statestyle.egg-info/pbr.json
latimes_statestyle.egg-info/top_level.txt
statestyle/__init__.py
statestyle/data.py