Metadata-Version: 1.1
Name: latimes-statestyle
Version: 0.1.6
Summary: Standardizes data about U.S. states
Home-page: UNKNOWN
Author: Ben Welsh
Author-email: ben.welsh@latimes.com
License: UNKNOWN
Platform: UNKNOWN
Classifier: Development Status :: 5 - Production/Stable
Classifier: Intended Audience :: Developers
Classifier: Programming Language :: Python :: 2
Classifier: Programming Language :: Python :: 2.7
Classifier: Programming Language :: Python :: 3
Classifier: Programming Language :: Python :: 3.1
Classifier: Programming Language :: Python :: 3.2
Classifier: Programming Language :: Python :: 3.3
Classifier: Programming Language :: Python :: 3.4
